{
	"animations": [
		{
			"loop": false,
			"offsets": [
				0,
				0
			],
			"anim": "idle",
			"fps": 24,
			"name": "idle",
			"indices": []
		},
		{
			"loop": true,
			"offsets": [
				160,
				1
			],
			"anim": "singLEFT",
			"fps": 24,
			"name": "left",
			"indices": []
		},
		{
			"loop": true,
			"offsets": [
				52,
				-180
			],
			"anim": "singDOWN",
			"fps": 24,
			"name": "down",
			"indices": []
		},
		{
			"loop": true,
			"offsets": [
				-12,
				-35
			],
			"anim": "singRIGHT",
			"fps": 24,
			"name": "right",
			"indices": []
		},
		{
			"loop": true,
			"offsets": [
				58,
				4
			],
			"anim": "singUP",
			"fps": 24,
			"name": "up",
			"indices": []
		}
	],
	"no_antialiasing": false,
	"image": "characters/hex",
	"position": [
		100,
		-10
	],
	"healthicon": "",
	"vocal_name": null,
	"flip_x": false,
	"healthbar_colors": [
		33,
		231,
		203
	],
	"camera_position": [
		20,
		190
	],
	"sing_duration": 4,
	"scale": 1.2
}